firebase_utils_jimmy/__init__.py
firebase_utils_jimmy/firestore_client.py
firebase_utils_jimmy-0.0.6.dist-info/LICENSE
firebase_utils_jimmy-0.0.6.dist-info/METADATA
firebase_utils_jimmy-0.0.6.dist-info/WHEEL
firebase_utils_jimmy-0.0.6.dist-info/top_level.txt
firebase_utils_jimmy-0.0.6.dist-info/RECORD
