Metadata-Version: 2.1
Name: firebase_utils_jimmy
Version: 0.0.6
Summary: Librería con funciones utiles y seguras para la interacción con Firestore.
Home-page: https://github.com/Serialk89/lib-python-base.git
Author: Jimmy Q
Author-email: jaime.quinones.t@gmail.com
Classifier: Programming Language :: Python :: 3
Classifier: License :: OSI Approved :: MIT License
Classifier: Operating System :: OS Independent
Requires-Python: >=3.11
License-File: LICENSE
Requires-Dist: firebase-admin
